MANIFEST.in
README.md
setup.py
Django_Notes.egg-info/PKG-INFO
Django_Notes.egg-info/SOURCES.txt
Django_Notes.egg-info/dependency_links.txt
Django_Notes.egg-info/not-zip-safe
Django_Notes.egg-info/top_level.txt
django_notes.egg-info/SOURCES.txt
notes/__init__.py
notes/admin.py
notes/forms.py
notes/managers.py
notes/models.py
notes/urls.py
notes/views.py
notes/templatetags/__init__.py
notes/templatetags/note_tags.py