Metadata-Version: 1.0
Name: django-notes
Version: 0.2.1
Summary: A simple reusable app to add notes to various models
Home-page: http://github.com/powellc/django-notes/
Author: Colin Powell
Author-email: colin@onecardinal.com
License: BSD
Platform: UNKNOWN
Classifier: Development Status :: 3 - Alpha
Classifier: Environment :: Web Environment
Classifier: Intended Audience :: Developers
Classifier: License :: OSI Approved :: BSD License
Classifier: Operating System :: OS Independent
Classifier: Programming Language :: Python
Classifier: Framework :: Django
